<SOAP-ENV:Envelope xmlns:SOAP-ENV="http://www.w3.org/2003/05/soap-envelope" xmlns:SOAP-ENC="http://www.w3.org/2003/05/soap-encoding" xmlns:xsi="http://www.w3.org/2001/XMLSchema-instance" xmlns:xsd="http://www.w3.org/2001/XMLSchema" xmlns:chan="http://schemas.microsoft.com/ws/2005/02/duplex" xmlns:wsa5="http://www.w3.org/2005/08/addressing" xmlns:c14n="http://www.w3.org/2001/10/xml-exc-c14n#" xmlns:wsu="http://docs.oasis-open.org/wss/2004/01/oasis-200401-wss-wssecurity-utility-1.0.xsd" xmlns:xenc="http://www.w3.org/2001/04/xmlenc#" xmlns:wsc="http://schemas.xmlsoap.org/ws/2005/02/sc" xmlns:ds="http://www.w3.org/2000/09/xmldsig#" xmlns:wsse="http://docs.oasis-open.org/wss/2004/01/oasis-200401-wss-wssecurity-secext-1.0.xsd" xmlns:xmime5="http://www.w3.org/2005/05/xmlmime" xmlns:xmime="http://tempuri.org/xmime.xsd" xmlns:xop="http://www.w3.org/2004/08/xop/include" xmlns:tt="http://www.onvif.org/ver10/schema" xmlns:wsrfbf="http://docs.oasis-open.org/wsrf/bf-2" xmlns:wstop="http://docs.oasis-open.org/wsn/t-1" xmlns:wsrfr="http://docs.oasis-open.org/wsrf/r-2" xmlns:tds="http://www.onvif.org/ver10/device/wsdl" xmlns:tev="http://www.onvif.org/ver10/events/wsdl" xmlns:wsnt="http://docs.oasis-open.org/wsn/b-2" xmlns:tptz="http://www.onvif.org/ver20/ptz/wsdl" xmlns:trt="http://www.onvif.org/ver10/media/wsdl" xmlns:timg="http://www.onvif.org/ver20/imaging/wsdl" xmlns:tmd="http://www.onvif.org/ver10/deviceIO/wsdl" xmlns:tns1="http://www.onvif.org/ver10/topics" xmlns:ter="http://www.onvif.org/ver10/error" xmlns:tnsaxis="http://www.axis.com/2009/event/topics">
    <SOAP-ENV:Header>
        <wsse:Security>
            <wsse:UsernameToken>
                <wsse:Username>admin</wsse:Username>
                <wsse:Password Type="http://docs.oasis-open.org/wss/2004/01/oasis-200401-wss-username-token-profile-1.0#PasswordDigest">fwb2EHRVv8DFlh4A9jLmSH+7VRs=</wsse:Password>
                <wsse:Nonce>MjEzNjQzMTMyNQ==</wsse:Nonce>
                <wsu:Created>2015-08-05T15:53:42.463Z</wsu:Created>
            </wsse:UsernameToken>
        </wsse:Security>
    </SOAP-ENV:Header>
    <SOAP-ENV:Body>
        <trt:CreateProfileResponse>
            <trt:Profile fixed="false" token="testToken">
                <tt:Name>test</tt:Name>
            </trt:Profile>
        </trt:CreateProfileResponse>
    </SOAP-ENV:Body>
</SOAP-ENV:Envelope>